{
  "pop_frac": [0.44, 0.35, 0.15, 0.06],
  "rate_frac": [1, 1, 1, 1],
  "rates": 2.3,
  "param": [
    {
      "intervention_date": "04-02-2020",
      "rate_frac": [0.2, 0.2, 0.2, 0.2],
      "intervention_type": "global"
    }
  ],
  "CFR": [0.02,0.08,0.12,0.25],
  "P_SEVERE": [0.04,  0.20, 0.24, 0.50],
  "I0": 50,
  "E0": 75,
  "D_death": 14,
  "D_hospital_lag": 5,
  "D_incubation": 5.2,
  "D_infectious": 2.9,
  "D_recovery_mild": 11.1,
  "D_recovery_severe": 28.6,
  "Fatal0": 0,
  "Mild0": 0,
  "R0": 0,
  "R_Fatal0": 0,
  "R_Mild0": 0,
  "R_Severe0": 0,
  "S0": -1,
  "Severe0": 0,
  "Severe_H0": 0
}
